setup.py
myweixin/__init__.py
myweixin/information.py
myweixin/multiprocess.py
myweixin.egg-info/PKG-INFO
myweixin.egg-info/SOURCES.txt
myweixin.egg-info/dependency_links.txt
myweixin.egg-info/requires.txt
myweixin.egg-info/top_level.txt